tpot2/__init__.py
tpot2/_version.py
tpot2/graphsklearn.py
tpot2/individual.py
tpot2/logbook.py
tpot2/population.py
tpot2/builtin_modules/__init__.py
tpot2/builtin_modules/arithmetictransformer.py
tpot2/builtin_modules/column_one_hot_encoder.py
tpot2/builtin_modules/estimatortransformer.py
tpot2/builtin_modules/feature_encoding_frequency_selector.py
tpot2/builtin_modules/feature_set_selector.py
tpot2/builtin_modules/feature_transformers.py
tpot2/builtin_modules/genetic_encoders.py
tpot2/builtin_modules/imputer.py
tpot2/builtin_modules/nn.py
tpot2/builtin_modules/passkbinsdiscretizer.py
tpot2/builtin_modules/passthrough.py
tpot2/builtin_modules/zero_count.py
tpot2/config/__init__.py
tpot2/config/autoqtl_builtins.py
tpot2/config/classifiers.py
tpot2/config/classifiers_sklearnex.py
tpot2/config/get_configspace.py
tpot2/config/imputers.py
tpot2/config/mdr_configs.py
tpot2/config/regressors.py
tpot2/config/regressors_sklearnex.py
tpot2/config/selectors.py
tpot2/config/special_configs.py
tpot2/config/template_search_spaces.py
tpot2/config/transformers.py
tpot2/config/tests/__init__.py
tpot2/config/tests/test_get_configspace.py
tpot2/evolvers/__init__.py
tpot2/evolvers/base_evolver.py
tpot2/evolvers/steady_state_evolver.py
tpot2/objectives/__init__.py
tpot2/objectives/average_path_length.py
tpot2/objectives/complexity.py
tpot2/objectives/number_of_leaves.py
tpot2/objectives/number_of_nodes.py
tpot2/old_config_utils/__init__.py
tpot2/old_config_utils/old_config_utils.py
tpot2/search_spaces/__init__.py
tpot2/search_spaces/base.py
tpot2/search_spaces/graph_utils.py
tpot2/search_spaces/tuple_index.py
tpot2/search_spaces/nodes/__init__.py
tpot2/search_spaces/nodes/estimator_node.py
tpot2/search_spaces/nodes/estimator_node_gradual.py
tpot2/search_spaces/nodes/fss_node.py
tpot2/search_spaces/nodes/genetic_feature_selection.py
tpot2/search_spaces/pipelines/__init__.py
tpot2/search_spaces/pipelines/choice.py
tpot2/search_spaces/pipelines/dynamic_linear.py
TPOT2-0.1.9a0.dist-info/LICENSE
TPOT2-0.1.9a0.dist-info/METADATA
TPOT2-0.1.9a0.dist-info/WHEEL
TPOT2-0.1.9a0.dist-info/entry_points.txt
TPOT2-0.1.9a0.dist-info/top_level.txt
TPOT2-0.1.9a0.dist-info/zip-safe
TPOT2-0.1.9a0.dist-info/RECORD
